<Process_Definition>
	<rolestart>
		DD
	</rolestart>
	<listgrup>
		1|Draft
	</listgrup>
	<listgrup>
		2|On Process
	</listgrup>
	<listgrup>
		3|Keputusan SPME
	</listgrup>
	<listgrup>
		4|Dibatalkan
	</listgrup>
	<variabel>
		<name>
			Nomor_Surat_Permohonan
		</name>
		<value1>
		</value1>
		<vtype>
			String
		</vtype>
	</variabel>
	<variabel>
		<name>
			Syarat_Umum
		</name>
		<value1>
		</value1>
		<value2>
		</value2>
		<vtype>
			file
		</vtype>
		<required>
			true
		</required>
		<linkfile>
			template-document/template-surat permohonan.pdf
		</linkfile>
	</variabel>
	<variabel>
		<name>
			Syarat_Khusus
		</name>
		<value1>
		</value1>
		<value2>
		</value2>
		<vtype>
			file
		</vtype>
		<required>
			true
		</required>
		<linkfile>
			template-document/template-surat permohonan.pdf
		</linkfile>
	</variabel>
	<variabel>
		<name>
			Assesor_1
		</name>
		<value1>
		</value1>
		<required>
			true
		</required>
		<value2>
		</value2>
		<vtype>
			Option
		</vtype>
	</variabel>
	<variabel>
		<name>
			Assesor_2
		</name>
		<value1>
		</value1>
		<required>
			true
		</required>
		<value2>
		</value2>
		<vtype>
			Option
		</vtype>
	</variabel>
	<variabel>
		<name>
			Jadwal_Assesment_Mulai
		</name>
		<required>
			true
		</required>
		<value1>
		</value1>
		<value2>
		</value2>
		<vtype>
			Date
		</vtype>
	</variabel>
	<variabel>
		<name>
			Jadwal_Assesment_Selesai
		</name>
		<required>
			true
		</required>
		<value1>
		</value1>
		<value2>
		</value2>
		<vtype>
			Date
		</vtype>
	</variabel>
	<variabel>
		<name>
			Laporan_Keuangan_Assesor_2
		</name>
		<value1>
		</value1>
		<value2>
		</value2>
		<vtype>
			file
		</vtype>
		<required>
			true
		</required>
		<linkfile>
			template-document/template-surat permohonan.pdf
		</linkfile>
	</variabel>
	<variabel>
		<name>
			Laporan_Keuangan_Assesor_1
		</name>
		<value1>
		</value1>
		<value2>
		</value2>
		<vtype>
			file
		</vtype>
		<required>
			true
		</required>
		<linkfile>
			template-document/template-surat permohonan.pdf
		</linkfile>
	</variabel>
	<variabel>
		<name>
			Laporan_Asesment_(include_berita_acara)_Assesor_1
		</name>
		<value1>
		</value1>
		<value2>
		</value2>
		<vtype>
			file
		</vtype>
		<required>
			true
		</required>
		<linkfile>
			template-document/template-surat permohonan.pdf
		</linkfile>
	</variabel>
	<variabel>
		<name>
			Laporan_Asesment_(include_berita_acara)_Assesor_2
		</name>
		<value1>
		</value1>
		<value2>
		</value2>
		<vtype>
			file
		</vtype>
		<required>
			true
		</required>
		<linkfile>
			template-document/template-surat permohonan.pdf
		</linkfile>
	</variabel>
	<variabel>
		<name>
			Berita_Acara_Visitasi
		</name>
		<value1>
		</value1>
		<value2>
		</value2>
		<vtype>
			file
		</vtype>
		<required>
			true
		</required>
		<linkfile>
			template-document/template-surat permohonan.pdf
		</linkfile>
	</variabel>
	<variabel>
		<name>
			Sertifikat_SPME
		</name>
		<value1>
		</value1>
		<value2>
		</value2>
		<vtype>
			file
		</vtype>
		<required>
			true
		</required>
		<linkfile>
			template-document/template-surat permohonan.pdf
		</linkfile>
	</variabel>
	<variabel>
		<name>
			Penilaian_SKL_1
		</name>
		<value1>
		</value1>
		<value2>
		</value2>
		<vtype>
			angket_asesment mahad'ali_SKL
		</vtype>
		<required>
			true
		</required>
	</variabel>
	<variabel>
		<name>
			Penilaian_SKL_2
		</name>
		<value1>
		</value1>
		<value2>
		</value2>
		<vtype>
			angket_asesment mahad'ali_SKL
		</vtype>
		<required>
			true
		</required>
	</variabel>
	<variabel>
		<name>
			Penilaian_Kurikulum_1
		</name>
		<value1>
		</value1>
		<value2>
		</value2>
		<vtype>
			angket_asesment mahad'ali_Kurikulum
		</vtype>
		<required>
			true
		</required>
	</variabel>
	<variabel>
		<name>
			Penilaian_Kurikulum_2
		</name>
		<value1>
		</value1>
		<value2>
		</value2>
		<vtype>
			angket_asesment mahad'ali_Kurikulum
		</vtype>
		<required>
			true
		</required>
	</variabel>
	<variabel>
		<name>
			PraVisitasi_lanjut_yes
		</name>
		<required>
			false
		</required>
		<value1>
			Ya
		</value1>
		<vtype>
			String
		</vtype>
	</variabel>
	<variabel>
		<name>
			PraVisitasi_lanjut_no
		</name>
		<required>
			false
		</required>
		<value1>
			Revisi Data
		</value1>
		<vtype>
			String
		</vtype>
	</variabel>
	<variabel>
		<name>
			Apakah_PraVisitasi_Asesor_1_Dapat_Dilanjutkan
		</name>
		<required>
			true
		</required>
		<value1>
			Ya
		</value1>
		<value2>
			Ya|Revisi Data
		</value2>
		<vtype>
			Option
		</vtype>
	</variabel>
	<variabel>
		<name>
			Apakah_PraVisitasi_Asesor_2_Dapat_Dilanjutkan
		</name>
		<required>
			true
		</required>
		<value1>
			Ya
		</value1>
		<value2>
			Ya|Revisi Data
		</value2>
		<vtype>
			Option
		</vtype>
	</variabel>
	<variabel>
		<name>
			Apakah_Visitasi_Asesor_1_Selesai
		</name>
		<required>
			true
		</required>
		<value1>
			Ya
		</value1>
		<value2>
			Ya|Tidak
		</value2>
		<vtype>
			Option
		</vtype>
	</variabel>
	<variabel>
		<name>
			Apakah_Visitasi_Asesor_2_Selesai
		</name>
		<required>
			true
		</required>
		<value1>
			Ya
		</value1>
		<value2>
			Ya|Tidak
		</value2>
		<vtype>
			Option
		</vtype>
	</variabel>
	<variabel>
		<name>
			Visitasi_selesai_yes
		</name>
		<required>
			false
		</required>
		<value1>
			Ya
		</value1>
		<vtype>
			String
		</vtype>
	</variabel>
	<variabel>
		<name>
			PraVisitasi_selesai_no
		</name>
		<required>
			false
		</required>
		<value1>
			Tidak
		</value1>
		<vtype>
			String
		</vtype>
	</variabel>
	<variabel>
		<name>
			Total_Nilai_Asesor_1
		</name>
		<value1>
		</value1>
		<value2>
		</value2>
		<vtype>
			statistik_asesment_form
		</vtype>
	</variabel>
	<variabel>
		<name>
			Sumary_data_visitasi_dikdasmen
		</name>
		<value1>
		</value1>
		<value2>
		</value2>
		<vtype>
			statistik_asesment_form
		</vtype>
	</variabel>
	<variabel>
		<name>
			totalnilai
		</name>
		<value1>
		</value1>
		<value2>
		</value2>
		<vtype>
			float
		</vtype>
	</variabel>
	<variabel>
		<name>
			Keputusan_Akhir_Peringkat_Asessment
		</name>
		<required>
			true
		</required>
		<value1>
		</value1>
		<value2>
			Mumtaz (Unggul)/A|Jayyid (Baik Sekali)/B|Maqbul (Baik)/C|Rasib (Tidak Lulus Asesmen)
		</value2>
		<vtype>
			Option
		</vtype>
	</variabel>
	<variabel>
		<name>
			status
		</name>
		<required>
			true
		</required>
		<value1>
		</value1>
		<value2>
			TIDAK MEMENUHI STANDAR MUTU.|MEMENUHI STANDAR MUTU.
		</value2>
		<vtype>
			Option
		</vtype>
	</variabel>
	<variabel>
		<name>
			Kualifikasi_Kepala_Satuan_Pendidikan_asesor1
		</name>
		<value1>
		</value1>
		<value2>
		</value2>
		<vtype>
			custom-formdata-wf_data_form_list-Kualifikasi_Kepala_Satuan_Pendidikan_asesor1
		</vtype>
		<label>
			true
		</label>
		<readonly>
			true
		</readonly>
	</variabel>
	<variabel>
		<name>
			Kualifikasi_Akademik_Pendidik_asesor1
		</name>
		<value1>
		</value1>
		<value2>
		</value2>
		<vtype>
			custom-formdata-wf_data_form_list-Kualifikasi_Akademik_Pendidik_asesor1
		</vtype>
		<label>
			true
		</label>
		<readonly>
			true
		</readonly>
	</variabel>
	<variabel>
		<name>
			Kualifikasi_Tenaga_Kependidikan_asesor1
		</name>
		<value1>
		</value1>
		<value2>
		</value2>
		<vtype>
			custom-formdata-wf_data_form_list-Kualifikasi_Tenaga_Kependidikan_asesor1
		</vtype>
		<label>
			true
		</label>
		<readonly>
			true
		</readonly>
	</variabel>
	<variabel>
		<name>
			Kualifikasi_Kepala_Satuan_Pendidikan_asesor2
		</name>
		<value1>
		</value1>
		<value2>
		</value2>
		<vtype>
			custom-formdata-wf_data_form_list-Kualifikasi_Kepala_Satuan_Pendidikan_asesor2
		</vtype>
		<label>
			true
		</label>
		<readonly>
			true
		</readonly>
	</variabel>
	<variabel>
		<name>
			Kualifikasi_Akademik_Pendidik_asesor2
		</name>
		<value1>
		</value1>
		<value2>
		</value2>
		<vtype>
			custom-formdata-wf_data_form_list-Kualifikasi_Akademik_Pendidik_asesor2
		</vtype>
		<label>
			true
		</label>
		<readonly>
			true
		</readonly>
	</variabel>
	<variabel>
		<name>
			Kualifikasi_Tenaga_Kependidikan_asesor2
		</name>
		<value1>
		</value1>
		<value2>
		</value2>
		<vtype>
			custom-formdata-wf_data_form_list-Kualifikasi_Tenaga_Kependidikan_asesor2
		</vtype>
		<label>
			true
		</label>
		<readonly>
			true
		</readonly>
	</variabel>
	<variabel>
		<name>
			Kualifikasi_Kepala_Satuan_Pendidikan_validasi
		</name>
		<value1>
		</value1>
		<value2>
		</value2>
		<vtype>
			custom-formdata-wf_data_form_list-Kualifikasi_Kepala_Satuan_Pendidikan_validasi
		</vtype>
		<label>
			true
		</label>
		<readonly>
			true
		</readonly>
	</variabel>
	<variabel>
		<name>
			Kualifikasi_Akademik_Pendidik_validasi
		</name>
		<value1>
		</value1>
		<value2>
		</value2>
		<vtype>
			custom-formdata-wf_data_form_list-Kualifikasi_Akademik_Pendidik_validasi
		</vtype>
		<label>
			true
		</label>
		<readonly>
			true
		</readonly>
	</variabel>
	<variabel>
		<name>
			Kualifikasi_Tenaga_Kependidikan_validasi
		</name>
		<value1>
		</value1>
		<value2>
		</value2>
		<vtype>
			custom-formdata-wf_data_form_list-Kualifikasi_Tenaga_Kependidikan_validasi
		</vtype>
		<label>
			true
		</label>
		<readonly>
			true
		</readonly>
	</variabel>
	<variabel>
		<name>
			Kualifikasi_Kepala_Satuan_Pendidikan_asesi
		</name>
		<value1>
		</value1>
		<value2>
		</value2>
		<vtype>
			custom-formdata-wf_data_form_list-Kualifikasi_Kepala_Satuan_Pendidikan_asesi
		</vtype>
		<label>
			true
		</label>
	</variabel>
	<variabel>
		<name>
			Kualifikasi_Akademik_Pendidik_asesi
		</name>
		<value1>
		</value1>
		<value2>
		</value2>
		<vtype>
			custom-formdata-wf_data_form_list-Kualifikasi_Akademik_Pendidik_asesi
		</vtype>
		<label>
			true
		</label>
	</variabel>
	<variabel>
		<name>
			Kualifikasi_Tenaga_Kependidikan_asesi
		</name>
		<value1>
		</value1>
		<value2>
		</value2>
		<vtype>
			custom-formdata-wf_data_form_list-Kualifikasi_Tenaga_Kependidikan_asesi
		</vtype>
		<label>
			true
		</label>
	</variabel>
	<variabel>
		<name>
			Pencapaian_Tujuan_Pendidikan_validasi
		</name>
		<value1>
		</value1>
		<value2>
		</value2>
		<vtype>
			custom-formlist-wf_data_form_level1-dd_PencapaianTujuanPendidikan_validasi
		</vtype>
	</variabel>
	<variabel>
		<name>
			Kepemimpinan_dan_Tata_Kelola_validasi
		</name>
		<value1>
		</value1>
		<value2>
		</value2>
		<vtype>
			custom-formlist-wf_data_form_level1-dd_KepemimpinandanTataKelola_validasi
		</vtype>
	</variabel>
	<variabel>
		<name>
			Kinerja_Pendidik_dalam_Pembelajaran_validasi
		</name>
		<value1>
		</value1>
		<value2>
		</value2>
		<vtype>
			custom-formlist-wf_data_form_level1-dd_KinerjaPendidikdalamPembelajaran_validasi
		</vtype>
	</variabel>
	<variabel>
		<name>
			Kepengasuhan_Pesantren_validasi
		</name>
		<value1>
		</value1>
		<value2>
		</value2>
		<vtype>
			custom-formlist-wf_data_form_level1-dd_KepengasuhanPesantren_validasi
		</vtype>
	</variabel>
	<variabel>
		<name>
			Pencapaian_Tujuan_Pendidikan_pleno
		</name>
		<value1>
		</value1>
		<value2>
		</value2>
		<vtype>
			custom-formlist-wf_data_form_level1-dd_PencapaianTujuanPendidikan_pleno
		</vtype>
	</variabel>
	<variabel>
		<name>
			Kepemimpinan_dan_Tata_Kelola_pleno
		</name>
		<value1>
		</value1>
		<value2>
		</value2>
		<vtype>
			custom-formlist-wf_data_form_level1-dd_KepemimpinandanTataKelola_pleno
		</vtype>
	</variabel>
	<variabel>
		<name>
			Kinerja_Pendidik_dalam_Pembelajaran_pleno
		</name>
		<value1>
		</value1>
		<value2>
		</value2>
		<vtype>
			custom-formlist-wf_data_form_level1-dd_KinerjaPendidikdalamPembelajaran_pleno
		</vtype>
	</variabel>
	<variabel>
		<name>
			Kepengasuhan_Pesantren_pleno
		</name>
		<value1>
		</value1>
		<value2>
		</value2>
		<vtype>
			custom-formlist-wf_data_form_level1-dd_KepengasuhanPesantren_pleno
		</vtype>
	</variabel>
	<variabel>
		<name>
			Pencapaian_Tujuan_Pendidikan_asesor1
		</name>
		<value1>
		</value1>
		<value2>
		</value2>
		<vtype>
			custom-formlist-wf_data_form_level1-dd_PencapaianTujuanPendidikan_asesor1
		</vtype>
	</variabel>
	<variabel>
		<name>
			Kepemimpinan_dan_Tata_Kelola_asesor1
		</name>
		<value1>
		</value1>
		<value2>
		</value2>
		<vtype>
			custom-formlist-wf_data_form_level1-dd_KepemimpinandanTataKelola_asesor1
		</vtype>
	</variabel>
	<variabel>
		<name>
			Kinerja_Pendidik_dalam_Pembelajaran_asesor1
		</name>
		<value1>
		</value1>
		<value2>
		</value2>
		<vtype>
			custom-formlist-wf_data_form_level1-dd_KinerjaPendidikdalamPembelajaran_asesor1
		</vtype>
	</variabel>
	<variabel>
		<name>
			Kepengasuhan_Pesantren_asesor1
		</name>
		<value1>
		</value1>
		<value2>
		</value2>
		<vtype>
			custom-formlist-wf_data_form_level1-dd_KepengasuhanPesantren_asesor1
		</vtype>
	</variabel>
	<variabel>
		<name>
			Pencapaian_Tujuan_Pendidikan_asesor2
		</name>
		<value1>
		</value1>
		<value2>
		</value2>
		<vtype>
			custom-formlist-wf_data_form_level1-dd_PencapaianTujuanPendidikan_asesor2
		</vtype>
	</variabel>
	<variabel>
		<name>
			Kepemimpinan_dan_Tata_Kelola_asesor2
		</name>
		<value1>
		</value1>
		<value2>
		</value2>
		<vtype>
			custom-formlist-wf_data_form_level1-dd_KepemimpinandanTataKelola_asesor2
		</vtype>
	</variabel>
	<variabel>
		<name>
			Kinerja_Pendidik_dalam_Pembelajaran_asesor2
		</name>
		<value1>
		</value1>
		<value2>
		</value2>
		<vtype>
			custom-formlist-wf_data_form_level1-dd_KinerjaPendidikdalamPembelajaran_asesor2
		</vtype>
	</variabel>
	<variabel>
		<name>
			Kepengasuhan_Pesantren_asesor2
		</name>
		<value1>
		</value1>
		<value2>
		</value2>
		<vtype>
			custom-formlist-wf_data_form_level1-dd_KepengasuhanPesantren_asesor2
		</vtype>
	</variabel>
	<variabel>
		<name>
			Pencapaian_Tujuan_Pendidikan_asesi
		</name>
		<value1>
		</value1>
		<value2>
		</value2>
		<vtype>
			custom-formlist-wf_data_form_level1-dd_PencapaianTujuanPendidikan_asesi
		</vtype>
	</variabel>
	<variabel>
		<name>
			Kepemimpinan_dan_Tata_Kelola_asesi
		</name>
		<value1>
		</value1>
		<value2>
		</value2>
		<vtype>
			custom-formlist-wf_data_form_level1-dd_KepemimpinandanTataKelola_asesi
		</vtype>
	</variabel>
	<variabel>
		<name>
			Kinerja_Pendidik_dalam_Pembelajaran_asesi
		</name>
		<value1>
		</value1>
		<value2>
		</value2>
		<vtype>
			custom-formlist-wf_data_form_level1-dd_KinerjaPendidikdalamPembelajaran_asesi
		</vtype>
	</variabel>
	<variabel>
		<name>
			Kepengasuhan_Pesantren_asesi
		</name>
		<value1>
		</value1>
		<value2>
		</value2>
		<vtype>
			custom-formlist-wf_data_form_level1-dd_KepengasuhanPesantren_asesi
		</vtype>
	</variabel>
	<variabel>
		<name>
			Pencapaian_Tujuan_Pendidikan_revisi
		</name>
		<value1>
		</value1>
		<value2>
		</value2>
		<vtype>
			custom-formlist-wf_data_form_level1-dd_PencapaianTujuanPendidikan_revisi
		</vtype>
	</variabel>
	<variabel>
		<name>
			Kepemimpinan_dan_Tata_Kelola_revisi
		</name>
		<value1>
		</value1>
		<value2>
		</value2>
		<vtype>
			custom-formlist-wf_data_form_level1-dd_KepemimpinandanTataKelola_revisi
		</vtype>
	</variabel>
	<variabel>
		<name>
			Kinerja_Pendidik_dalam_Pembelajaran_revisi
		</name>
		<value1>
		</value1>
		<value2>
		</value2>
		<vtype>
			custom-formlist-wf_data_form_level1-dd_KinerjaPendidikdalamPembelajaran_revisi
		</vtype>
	</variabel>
	<variabel>
		<name>
			Kepengasuhan_Pesantren_revisi
		</name>
		<value1>
		</value1>
		<value2>
		</value2>
		<vtype>
			custom-formlist-wf_data_form_level1-dd_KepengasuhanPesantren_revisi
		</vtype>
	</variabel>
	<variabel>
		<name>
			Pencapaian_Tujuan_Pendidikan_cek
		</name>
		<value1>
		</value1>
		<value2>
		</value2>
		<vtype>
			custom-formlist-wf_data_form_level1-dd_PencapaianTujuanPendidikan_cek
		</vtype>
	</variabel>
	<variabel>
		<name>
			Kepemimpinan_dan_Tata_Kelola_cek
		</name>
		<value1>
		</value1>
		<value2>
		</value2>
		<vtype>
			custom-formlist-wf_data_form_level1-dd_KepemimpinandanTataKelola_cek
		</vtype>
	</variabel>
	<variabel>
		<name>
			Kinerja_Pendidik_dalam_Pembelajaran_cek
		</name>
		<value1>
		</value1>
		<value2>
		</value2>
		<vtype>
			custom-formlist-wf_data_form_level1-dd_KinerjaPendidikdalamPembelajaran_cek
		</vtype>
	</variabel>
	<variabel>
		<name>
			Kepengasuhan_Pesantren_cek
		</name>
		<value1>
		</value1>
		<value2>
		</value2>
		<vtype>
			custom-formlist-wf_data_form_level1-dd_KepengasuhanPesantren_cek
		</vtype>
	</variabel>
	<variabel>
		<name>
			Pencapaian_Tujuan_Pendidikan_hasil
		</name>
		<value1>
		</value1>
		<value2>
		</value2>
		<vtype>
			custom-formlist-wf_data_form_level1-dd_PencapaianTujuanPendidikan_hasil
		</vtype>
	</variabel>
	<variabel>
		<name>
			Kepemimpinan_dan_Tata_Kelola_hasil
		</name>
		<value1>
		</value1>
		<value2>
		</value2>
		<vtype>
			custom-formlist-wf_data_form_level1-dd_KepemimpinandanTataKelola_hasil
		</vtype>
	</variabel>
	<variabel>
		<name>
			Kinerja_Pendidik_dalam_Pembelajaran_hasil
		</name>
		<value1>
		</value1>
		<value2>
		</value2>
		<vtype>
			custom-formlist-wf_data_form_level1-dd_KinerjaPendidikdalamPembelajaran_hasil
		</vtype>
	</variabel>
	<variabel>
		<name>
			Kepengasuhan_Pesantren_hasil
		</name>
		<value1>
		</value1>
		<value2>
		</value2>
		<vtype>
			custom-formlist-wf_data_form_level1-dd_KepengasuhanPesantren_hasil
		</vtype>
	</variabel>
	<variabel>
		<name>
			Informasi_Syarat_Utama_dan_Khusus_validasi
		</name>
		<value1>
		</value1>
		<value2>
		</value2>
		<vtype>
			custom-formlist-wf_data_form_level1-dd_InformasiSyaratUtamadanKhusus_validasi
		</vtype>
		<label>
			true
		</label>
	</variabel>
	<variabel>
		<name>
			Sarana_Dan_Prasrana_Penunjang_Kegiatan_Pembelajaran_validasi
		</name>
		<value1>
		</value1>
		<value2>
		</value2>
		<vtype>
			custom-formlist-wf_data_form_level1-dd_SaranaDanPrasranaPenunjangKegiatanPembelajaran_validasi
		</vtype>
		<label>
			true
		</label>
	</variabel>
	<variabel>
		<name>
			Sarana_Dan_Prasarana_Penunjang_Pengasuhan_validasi
		</name>
		<value1>
		</value1>
		<value2>
		</value2>
		<vtype>
			custom-formlist-wf_data_form_level1-dd_SaranaDanPrasaranaPenunjangPengasuhan_validasi
		</vtype>
		<label>
			true
		</label>
	</variabel>
	<variabel>
		<name>
			Informasi_Statistik_Rasio_Santri_Dan_Pendidik_validasi
		</name>
		<value1>
		</value1>
		<value2>
		</value2>
		<vtype>
			custom-formlist-wf_data_form_level1-dd_InformasiStatistikRasioSantriDanPendidik_validasi
		</vtype>
		<label>
			true
		</label>
	</variabel>
	<variabel>
		<name>
			Informasi_Syarat_Utama_dan_Khusus_asesor1
		</name>
		<value1>
		</value1>
		<value2>
		</value2>
		<vtype>
			custom-formlist-wf_data_form_level1-dd_InformasiSyaratUtamadanKhusus_asesor1
		</vtype>
		<label>
			true
		</label>
	</variabel>
	<variabel>
		<name>
			Sarana_Dan_Prasrana_Penunjang_Kegiatan_Pembelajaran_asesor1
		</name>
		<value1>
		</value1>
		<value2>
		</value2>
		<vtype>
			custom-formlist-wf_data_form_level1-dd_SaranaDanPrasranaPenunjangKegiatanPembelajaran_asesor1
		</vtype>
		<label>
			true
		</label>
	</variabel>
	<variabel>
		<name>
			Sarana_Dan_Prasarana_Penunjang_Pengasuhan_asesor1
		</name>
		<value1>
		</value1>
		<value2>
		</value2>
		<vtype>
			custom-formlist-wf_data_form_level1-dd_SaranaDanPrasaranaPenunjangPengasuhan_asesor1
		</vtype>
		<label>
			true
		</label>
	</variabel>
	<variabel>
		<name>
			Informasi_Statistik_Rasio_Santri_Dan_Pendidik_asesor1
		</name>
		<value1>
		</value1>
		<value2>
		</value2>
		<vtype>
			custom-formlist-wf_data_form_level1-dd_InformasiStatistikRasioSantriDanPendidik_asesor1
		</vtype>
		<label>
			true
		</label>
	</variabel>
	<variabel>
		<name>
			Informasi_Syarat_Utama_dan_Khusus_asesor2
		</name>
		<value1>
		</value1>
		<value2>
		</value2>
		<vtype>
			custom-formlist-wf_data_form_level1-dd_InformasiSyaratUtamadanKhusus_asesor2
		</vtype>
		<label>
			true
		</label>
	</variabel>
	<variabel>
		<name>
			Sarana_Dan_Prasrana_Penunjang_Kegiatan_Pembelajaran_asesor2
		</name>
		<value1>
		</value1>
		<value2>
		</value2>
		<vtype>
			custom-formlist-wf_data_form_level1-dd_SaranaDanPrasranaPenunjangKegiatanPembelajaran_asesor2
		</vtype>
		<label>
			true
		</label>
	</variabel>
	<variabel>
		<name>
			Sarana_Dan_Prasarana_Penunjang_Pengasuhan_asesor2
		</name>
		<value1>
		</value1>
		<value2>
		</value2>
		<vtype>
			custom-formlist-wf_data_form_level1-dd_SaranaDanPrasaranaPenunjangPengasuhan_asesor2
		</vtype>
		<label>
			true
		</label>
	</variabel>
	<variabel>
		<name>
			Informasi_Statistik_RasioSantri_Dan_Pendidik_asesor2
		</name>
		<value1>
		</value1>
		<value2>
		</value2>
		<vtype>
			custom-formlist-wf_data_form_level1-dd_InformasiStatistikRasioSantriDanPendidik_asesor2
		</vtype>
		<label>
			true
		</label>
	</variabel>
	<variabel>
		<name>
			Informasi_Syarat_Utama_dan_Khusus_asesi
		</name>
		<value1>
		</value1>
		<value2>
		</value2>
		<vtype>
			custom-formlist-wf_data_form_level1-dd_InformasiSyaratUtamadanKhusus_asesi
		</vtype>
		<label>
			true
		</label>
	</variabel>
	<variabel>
		<name>
			Sarana_Dan_Prasrana_Penunjang_Kegiatan_Pembelajaran_asesi
		</name>
		<value1>
		</value1>
		<value2>
		</value2>
		<vtype>
			custom-formlist-wf_data_form_level1-dd_SaranaDanPrasranaPenunjangKegiatanPembelajaran_asesi
		</vtype>
		<label>
			true
		</label>
	</variabel>
	<variabel>
		<name>
			Sarana_Dan_Prasarana_Penunjang_Pengasuhan_asesi
		</name>
		<value1>
		</value1>
		<value2>
		</value2>
		<vtype>
			custom-formlist-wf_data_form_level1-dd_SaranaDanPrasaranaPenunjangPengasuhan_asesi
		</vtype>
		<label>
			true
		</label>
	</variabel>
	<variabel>
		<name>
			Informasi_Statistik_Rasio_Santri_Dan_Pendidik_asesi
		</name>
		<value1>
		</value1>
		<value2>
		</value2>
		<vtype>
			custom-formlist-wf_data_form_level1-dd_InformasiStatistikRasioSantriDanPendidik_asesi
		</vtype>
		<label>
			true
		</label>
	</variabel>
	<variabel>
		<name>
			Nama_Satuan_Pendidikan
		</name>
		<required>
			false
		</required>
		<value1>
		</value1>
		<value2>
		</value2>
		<vtype>
			String
		</vtype>
	</variabel>
	<variabel>
		<name>
			NPSN
		</name>
		<required>
			false
		</required>
		<value1>
		</value1>
		<value2>
		</value2>
		<vtype>
			String
		</vtype>
	</variabel>
	<variabel>
		<name>
			Jenjang
		</name>
		<required>
			false
		</required>
		<value1>
		</value1>
		<value2>
			ula|wustho|ulya
		</value2>
		<vtype>
			option
		</vtype>
	</variabel>
	<variabel>
		<name>
			Nama_Pesantren
		</name>
		<required>
			false
		</required>
		<value1>
		</value1>
		<value2>
		</value2>
		<vtype>
			String
		</vtype>
	</variabel>
	<variabel>
		<name>
			Tahun_Berdiri
		</name>
		<required>
			false
		</required>
		<value1>
		</value1>
		<value2>
		</value2>
		<vtype>
			String
		</vtype>
	</variabel>
	<variabel>
		<name>
			Nomor_Statistik_Pesantren
		</name>
		<required>
			false
		</required>
		<value1>
		</value1>
		<value2>
		</value2>
		<vtype>
			String
		</vtype>
	</variabel>
	<variabel>
		<name>
			Alamat
		</name>
		<required>
			false
		</required>
		<value1>
		</value1>
		<value2>
		</value2>
		<vtype>
			String
		</vtype>
	</variabel>
	<variabel>
		<name>
			Email
		</name>
		<required>
			false
		</required>
		<value1>
		</value1>
		<value2>
		</value2>
		<vtype>
			String
		</vtype>
	</variabel>
	<variabel>
		<name>
			Contact_Person
		</name>
		<required>
			false
		</required>
		<value1>
		</value1>
		<value2>
		</value2>
		<vtype>
			String
		</vtype>
	</variabel>
	<variabel>
		<name>
			Pimpinan_Pesantren
		</name>
		<required>
			false
		</required>
		<value1>
		</value1>
		<value2>
		</value2>
		<vtype>
			String
		</vtype>
	</variabel>
	<variabel>
		<name>
			Pendiri_Pesantren
		</name>
		<required>
			false
		</required>
		<value1>
		</value1>
		<value2>
		</value2>
		<vtype>
			String
		</vtype>
	</variabel>
	<variabel>
		<name>
			Ketua_Dewan_Masyayikh
		</name>
		<required>
			false
		</required>
		<value1>
		</value1>
		<value2>
		</value2>
		<vtype>
			String
		</vtype>
	</variabel>
	<variabel>
		<name>
			Kepala_Satuan_Pendidikan
		</name>
		<required>
			false
		</required>
		<value1>
		</value1>
		<value2>
		</value2>
		<vtype>
			String
		</vtype>
	</variabel>
	<variabel>
		<name>
			Hasil_Akreditasi_Sebelumnya
		</name>
		<required>
			false
		</required>
		<value1>
		</value1>
		<value2>
		</value2>
		<vtype>
			String
		</vtype>
	</variabel>
	<variabel>
		<name>
			Masa_Berlaku_Akreditasi_Sebelumnya
		</name>
		<required>
			false
		</required>
		<value1>
		</value1>
		<value2>
		</value2>
		<vtype>
			String
		</vtype>
	</variabel>
	<variabel>
		<name>
			Tahun_Periode_Asesmen
		</name>
		<required>
			false
		</required>
		<value1>
		</value1>
		<value2>
		</value2>
		<vtype>
			String
		</vtype>
	</variabel>
	<variabel>
		<name>
			Waktu_Pelaksanaan_Visitasi_Lapangan
		</name>
		<required>
			false
		</required>
		<value1>
		</value1>
		<value2>
		</value2>
		<vtype>
			Date
		</vtype>
	</variabel>
	<variabel>
		<name>
			Hasil_Pravisitasi
		</name>
		<required>
			false
		</required>
		<value1>
			[notiket]-1000
		</value1>
		<value2>
		</value2>
		<vtype>
			Redirect
		</vtype>
		<readonly>
			true
		</readonly>
	</variabel>
	<step>
		<number>
			0
		</number>
		<type>
			form
		</type>
		<title>
			Draft Pengajuan
		</title>
		<form_data_input>
			{"Nama_Pesantren": "","Tahun_Berdiri": "" ,"Nomor_Statistik_Pesantren": "","Nama_Satuan_Pendidikan": "","NPSN": "","Jenjang": "","Alamat": "","Email": "","Contact_Person": "","Pimpinan_Pesantren": "","Pendiri_Pesantren": "","Ketua_Dewan_Masyayikh": "","Kepala_Satuan_Pendidikan": "","Tahun_Periode_Asesmen": ""}
		</form_data_input>
		<decision_key>
			{"true":"Lanjutkan", "false": "Batalkan Tiket", "save": "Simpan" }
		</decision_key>
		<status>
			Draft
		</status>
		<grup>
			Draft
		</grup>
		<statustiket>
			Draft
		</statustiket>
		<logstart>
			Draft Dibuat,Pengajuan SPME mulai dibuat oleh [dd]
		</logstart>
		<logfalse>
			Draft Dibatalkan, Pengajuan dibatalkan oleh [dd]
		</logfalse>
		<steptrue>
			1
		</steptrue>
		<stepfalse>
			46
		</stepfalse>
	</step>
	<step>
		<number>
			1
		</number>
		<type>
			system_update_satuan_pendidikan
		</type>
		<title>
		</title>
		<form_data_input>
			Nama_Satuan_Pendidikan
		</form_data_input>
		<steptrue>
			2
		</steptrue>
		<stepfalse>
			0
		</stepfalse>
	</step>
	<step>
		<number>
			2
		</number>
		<role>
			DD
		</role>
		<type>
			form
		</type>
		<title>
			Draft Complianc
		</title>
		<form_data_view>
			{"Informasi_Pengajuan_DIKDASMEN": "" }
		</form_data_view>
		<form_data_input>
			{"Informasi_Syarat_Utama_dan_Khusus_asesi": "","Kualifikasi_Kepala_Satuan_Pendidikan_asesi": "","Kualifikasi_Akademik_Pendidik_asesi": "","Kualifikasi_Tenaga_Kependidikan_asesi": "","Sarana_Dan_Prasrana_Penunjang_Kegiatan_Pembelajaran_asesi": "","Sarana_Dan_Prasarana_Penunjang_Pengasuhan_asesi": "","Informasi_Statistik_Rasio_Santri_Dan_Pendidik_asesi": "" }
		</form_data_input>
		<decision_key>
			{"true":"Lanjutkan", "false": "Kembali", "save": "Simpan" }
		</decision_key>
		<status>
			Draft
		</status>
		<grup>
			Draft
		</grup>
		<statustiket>
			Draft
		</statustiket>
		<steptrue>
			3
		</steptrue>
		<stepfalse>
			0
		</stepfalse>
	</step>
	<step>
		<number>
			3
		</number>
		<type>
			form
		</type>
		<role>
			DD
		</role>
		<title>
			Draft Standar Kompetensi Lulusan
		</title>
		<form_data_view>
			{"Informasi_Pengajuan_DIKDASMEN": "" }
		</form_data_view>
		<form_data_input>
			{"Pencapaian_Tujuan_Pendidikan_asesi": ""}
		</form_data_input>
		<decision_key>
			{"true":"Lanjutkan", "false": "Kembali", "save": "Simpan" }
		</decision_key>
		<status>
			Draft
		</status>
		<grup>
			Draft
		</grup>
		<statustiket>
			Draft
		</statustiket>
		<steptrue>
			4
		</steptrue>
		<stepfalse>
			2
		</stepfalse>
	</step>
	<step>
		<number>
			4
		</number>
		<type>
			form
		</type>
		<role>
			DD
		</role>
		<title>
			Draft Standar Kurikulum
		</title>
		<form_data_view>
			{"Informasi_Pengajuan_DIKDASMEN": "" }
		</form_data_view>
		<form_data_input>
			{"Kepemimpinan_dan_Tata_Kelola_asesi": "" }
		</form_data_input>
		<decision_key>
			{"true":"Lanjutkan", "false": "Kembali", "save": "Simpan" }
		</decision_key>
		<status>
			Draft
		</status>
		<grup>
			Draft
		</grup>
		<statustiket>
			Draft
		</statustiket>
		<steptrue>
			5
		</steptrue>
		<stepfalse>
			3
		</stepfalse>
	</step>
	<step>
		<number>
			5
		</number>
		<type>
			form
		</type>
		<role>
			DD
		</role>
		<title>
			Draft Standar Pendidik dan Tenaga Kependidikan
		</title>
		<form_data_view>
			{"Informasi_Pengajuan_DIKDASMEN": "" }
		</form_data_view>
		<form_data_input>
			{"Kinerja_Pendidik_dalam_Pembelajaran_asesi": "" }
		</form_data_input>
		<decision_key>
			{"true":"Lanjutkan", "false": "Kembali", "save": "Simpan" }
		</decision_key>
		<status>
			Draft
		</status>
		<grup>
			Draft
		</grup>
		<statustiket>
			Draft
		</statustiket>
		<steptrue>
			6
		</steptrue>
		<stepfalse>
			4
		</stepfalse>
	</step>
	<step>
		<number>
			6
		</number>
		<type>
			form
		</type>
		<role>
			DD
		</role>
		<title>
			Draft Standar Kelembagaan
		</title>
		<form_data_view>
			{"Informasi_Pengajuan_DIKDASMEN": "" }
		</form_data_view>
		<form_data_input>
			{"Kepengasuhan_Pesantren_asesi": ""}
		</form_data_input>
		<decision_key>
			{"true":"Kirim Pengajuan", "false": "Kembali", "save": "Simpan" }
		</decision_key>
		<status>
			Draft
		</status>
		<grup>
			Draft
		</grup>
		<statustiket>
			Draft
		</statustiket>
		<logtrue>
			Draft Dikirim, Dokumen SPME diajukan dan dikirim oleh [dd]
		</logtrue>
		<steptrue>
			7
		</steptrue>
		<stepfalse>
			5
		</stepfalse>
	</step>
	<step>
		<number>
			7
		</number>
		<type>
			system_role_list_user
		</type>
		<title>
			DS
		</title>
		<form_data_input>
			Assesor_1
		</form_data_input>
		<steptrue>
			8
		</steptrue>
		<stepfalse>
			0
		</stepfalse>
	</step>
	<step>
		<number>
			8
		</number>
		<type>
			system_role_list_user
		</type>
		<title>
			DS
		</title>
		<form_data_input>
			Assesor_2
		</form_data_input>
		<steptrue>
			9
		</steptrue>
		<stepfalse>
			0
		</stepfalse>
	</step>
	<step>
		<number>
			9
		</number>
		<role>
			SK
		</role>
		<type>
			form
		</type>
		<title>
			Penunjukan Asesor dan Jadwal Assesment
		</title>
		<form_data_input>
			{"Assesor_1": "", "Assesor_2": "", "Jadwal_Assesment_Mulai": "", "Jadwal_Assesment_Selesai": "" }
		</form_data_input>
		<form_data_view>
			{"Informasi_Pengajuan_DIKDASMEN": "","Nama_Satuan_Pendidikan": "","NPSN": "" ,"jenjang": "" }
		</form_data_view>
		<decision_key>
			{"true":"Lanjutkan" }
		</decision_key>
		<status>
			Sedang Diproses
		</status>
		<grup>
			On Process
		</grup>
		<statustiket>
			On Process
		</statustiket>
		<logstart>
			Penunjukan Asesor dan Jadwal Assesment,Dokumen kamu dalam proses penunjukan assesor oleh Sekretariat MM
		</logstart>
		<logtrue>
			Penunjukan Asesor dan Jadwal Assesment,Assesor dokumen kamu sudah ditentukan oleh Sekretariat MM
		</logtrue>
		<steptrue>
			10
		</steptrue>
		<stepfalse>
			0
		</stepfalse>
	</step>
	<step>
		<number>
			10
		</number>
		<role>
			DS
		</role>
		<type>
			system_system_role_pic_pick
		</type>
		<title>
			Assesor_1
		</title>
		<form_data_input>
			12,14,20,21,22,23,52
		</form_data_input>
		<steptrue>
			11
		</steptrue>
		<stepfalse>
			0
		</stepfalse>
	</step>
	<step>
		<number>
			11
		</number>
		<role>
			DS
		</role>
		<type>
			system_system_role_pic_pick
		</type>
		<title>
			Assesor_2
		</title>
		<form_data_input>
			13,15,24,25,26,27,51
		</form_data_input>
		<steptrue>
			50
		</steptrue>
		<stepfalse>
			0
		</stepfalse>
	</step>
	<step>
		<number>
			50
		</number>
		<role>
			Assesor_2,Assesor_1
		</role>
		<type>
			system_email_user
		</type>
		<title>
			Pengajuan Rekomendasi
		</title>
		<form_data_input>
			Terdapat asessmen DIKDASMEN untuk nomer tiket [notiket] diajukan dari [variabel_Nama_Satuan_Pendidikan]. Silahkan buka SYAMIL untuk melanjutkan proses PRAVISITASI.
		</form_data_input>
		<steptrue>
			12;13
		</steptrue>
		<stepfalse>
			0
		</stepfalse>
	</step>
	<step>
		<number>
			12
		</number>
		<role>
			DS
		</role>
		<type>
			form
		</type>
		<title>
			Penilaian Pra Visitasi Asesor 1
		</title>
		<viewer>
			SK,AD
		</viewer>
		<form_data_view>
			{"Informasi_Pengajuan_DIKDASMEN": "","Assesor_1": "","Assesor_2": "" }
		</form_data_view>
		<form_data_input>
			{"Nama_Pesantren": "","Tahun_Berdiri": "" ,"Nomor_Statistik_Pesantren": "","Nama_Satuan_Pendidikan": "","NPSN": "","Jenjang": "","Alamat": "","Email": "","Contact_Person": "","Pimpinan_Pesantren": "","Pendiri_Pesantren": "","Ketua_Dewan_Masyayikh": "","Kepala_Satuan_Pendidikan": "","Hasil_Akreditasi_Sebelumnya": "","Masa_Berlaku_Akreditasi_Sebelumnya": "","Tahun_Periode_Asesmen": "","Waktu_Pelaksanaan_Visitasi_Lapangan": ""}
		</form_data_input>
		<decision_key>
			{"true":"Lanjutkan"}
		</decision_key>
		<statustiket>
			On Process
		</statustiket>
		<logstart>
			Penilaian Pra Visitasi,Dokumen kamu dalam proses penilaian pra-visitasi oleh Assesor 1
		</logstart>
		<steptrue>
			14
		</steptrue>
		<stepfalse>
			0
		</stepfalse>
	</step>
	<step>
		<number>
			13
		</number>
		<role>
			DS
		</role>
		<type>
			form
		</type>
		<title>
			Penilaian Pra Visitasi Asesor 2
		</title>
		<viewer>
			SK,AD
		</viewer>
		<form_data_view>
			{"Informasi_Pengajuan_DIKDASMEN": "" ,"Assesor_1": "","Assesor_2": ""}
		</form_data_view>
		<form_data_input>
			{"Nama_Pesantren": "","Tahun_Berdiri": "" ,"Nomor_Statistik_Pesantren": "","Nama_Satuan_Pendidikan": "","NPSN": "","Jenjang": "","Alamat": "","Email": "","Contact_Person": "","Pimpinan_Pesantren": "","Pendiri_Pesantren": "","Ketua_Dewan_Masyayikh": "","Kepala_Satuan_Pendidikan": "","Hasil_Akreditasi_Sebelumnya": "","Masa_Berlaku_Akreditasi_Sebelumnya": "","Tahun_Periode_Asesmen": "","Waktu_Pelaksanaan_Visitasi_Lapangan": "" }
		</form_data_input>
		<decision_key>
			{"true":"Lanjutkan"}
		</decision_key>
		<statustiket>
			On Process
		</statustiket>
		<logstart>
			Penilaian Pra Visitasi,Dokumen kamu dalam proses penilaian pra-visitasi oleh Assesor 2
		</logstart>
		<steptrue>
			15
		</steptrue>
		<stepfalse>
			0
		</stepfalse>
	</step>
	<step>
		<number>
			14
		</number>
		<role>
			DS
		</role>
		<type>
			form
		</type>
		<title>
			Penilaian Pra Visitasi Asesor 1
		</title>
		<viewer>
			SK,AD
		</viewer>
		<form_data_view>
			{"Informasi_Pengajuan_DIKDASMEN": "" }
		</form_data_view>
		<form_data_input>
			{"Informasi_Syarat_Utama_dan_Khusus_asesor1": "","Kualifikasi_Kepala_Satuan_Pendidikan_asesor1": "","Kualifikasi_Akademik_Pendidik_asesor1": "","Kualifikasi_Tenaga_Kependidikan_asesor1": "","Sarana_Dan_Prasrana_Penunjang_Kegiatan_Pembelajaran_asesor1": "","Sarana_Dan_Prasarana_Penunjang_Pengasuhan_asesor1": "","Informasi_Statistik_Rasio_Santri_Dan_Pendidik_asesor1":"" }
		</form_data_input>
		<decision_key>
			{"true":"Selesai", "false": "Kembali", "save": "Simpan" }
		</decision_key>
		<statustiket>
			On Process
		</statustiket>
		<logtrue>
			Penilaian Pra Visitasi,Dokumen kamu selesai proses penilaian pra-visitasi oleh Assesor 1
		</logtrue>
		<steptrue>
			20
		</steptrue>
		<stepfalse>
			12
		</stepfalse>
	</step>
	<step>
		<number>
			15
		</number>
		<role>
			DS
		</role>
		<type>
			form
		</type>
		<title>
			Penilaian Pra Visitasi Asesor 2
		</title>
		<viewer>
			SK,AD
		</viewer>
		<form_data_view>
			{"Informasi_Pengajuan_DIKDASMEN": "" }
		</form_data_view>
		<form_data_input>
			{"Informasi_Syarat_Utama_dan_Khusus_asesor2": "","Kualifikasi_Kepala_Satuan_Pendidikan_asesor2": "","Kualifikasi_Akademik_Pendidik_asesor2": "","Kualifikasi_Tenaga_Kependidikan_asesor2": "","Sarana_Dan_Prasrana_Penunjang_Kegiatan_Pembelajaran_asesor2": "","Sarana_Dan_Prasarana_Penunjang_Pengasuhan_asesor2": "","Informasi_Statistik_Rasio_Santri_Dan_Pendidik_asesor2":""}
		</form_data_input>
		<decision_key>
			{"true":"Selesai", "false": "Kembali", "save": "Simpan" }
		</decision_key>
		<statustiket>
			On Process
		</statustiket>
		<logtrue>
			Penilaian Pra Visitasi,Dokumen kamu selesai proses penilaian pra-visitasi oleh Assesor 2
		</logtrue>
		<steptrue>
			24
		</steptrue>
		<stepfalse>
			13
		</stepfalse>
	</step>
	<step>
		<number>
			20
		</number>
		<type>
			form
		</type>
		<role>
			DS
		</role>
		<title>
			Penilaian Visitasi Standar Kompetensi Lulusan Asesor 1
		</title>
		<viewer>
			SK,AD
		</viewer>
		<form_data_view>
			{"Informasi_Pengajuan_DIKDASMEN": "","Hasil_Pravisitasi":"" }
		</form_data_view>
		<form_data_input>
			{"Pencapaian_Tujuan_Pendidikan_asesor1": ""}
		</form_data_input>
		<decision_key>
			{"true":"Lanjutkan", "save": "Simpan"}
		</decision_key>
		<statustiket>
			On Process
		</statustiket>
		<logstart>
			Penilaian Visitasi,Dokumen kamu dalam proses penilaian visitasi oleh Assesor 1
		</logstart>
		<steptrue>
			21
		</steptrue>
		<stepfalse>
			14
		</stepfalse>
	</step>
	<step>
		<number>
			21
		</number>
		<type>
			form
		</type>
		<role>
			DS
		</role>
		<title>
			Penilaian Visitasi Standar Kurikulum Asesor 1
		</title>
		<viewer>
			SK,AD
		</viewer>
		<form_data_view>
			{"Informasi_Pengajuan_DIKDASMEN": "" ,"Hasil_Pravisitasi":""}
		</form_data_view>
		<form_data_input>
			{"Kepemimpinan_dan_Tata_Kelola_asesor1": "" }
		</form_data_input>
		<decision_key>
			{"true":"Lanjutkan", "save": "Simpan", "false": "Kembali"}
		</decision_key>
		<statustiket>
			On Process
		</statustiket>
		<steptrue>
			22
		</steptrue>
		<stepfalse>
			20
		</stepfalse>
	</step>
	<step>
		<number>
			22
		</number>
		<type>
			form
		</type>
		<role>
			DS
		</role>
		<title>
			Penilaian Visitasi Standar Pendidik dan Tenaga Kependidikan Asesor 1
		</title>
		<viewer>
			SK,AD
		</viewer>
		<form_data_view>
			{"Informasi_Pengajuan_DIKDASMEN": "" ,"Hasil_Pravisitasi":""}
		</form_data_view>
		<form_data_input>
			{"Kinerja_Pendidik_dalam_Pembelajaran_asesor1": "" }
		</form_data_input>
		<decision_key>
			{"true":"Lanjutkan", "save": "Simpan", "false": "Kembali"}
		</decision_key>
		<statustiket>
			On Process
		</statustiket>
		<steptrue>
			23
		</steptrue>
		<stepfalse>
			21
		</stepfalse>
	</step>
	<step>
		<number>
			23
		</number>
		<type>
			form
		</type>
		<role>
			DS
		</role>
		<title>
			Penilaian Visitasi Standar Kelembagaan Asesor 1
		</title>
		<viewer>
			SK,AD
		</viewer>
		<form_data_view>
			{"Informasi_Pengajuan_DIKDASMEN": "" ,"Hasil_Pravisitasi":""}
		</form_data_view>
		<form_data_input>
			{"Kepengasuhan_Pesantren_asesor1": "" }
		</form_data_input>
		<decision_key>
			{"true":"Lanjutkan", "save": "Simpan", "false": "Kembali"}
		</decision_key>
		<statustiket>
			On Process
		</statustiket>
		<logtrue>
			Penilaian Visitasi,Dokumen kamu selesai proses penilaian visitasi oleh Assesor 1
		</logtrue>
		<steptrue>
			52
		</steptrue>
		<stepfalse>
			22
		</stepfalse>
	</step>
	<step>
		<number>
			52
		</number>
		<type>
			form
		</type>
		<role>
			DS
		</role>
		<title>
			Penilaian Visitasi Asesor 1
		</title>
		<viewer>
			SK,AD
		</viewer>
		<form_data_view>
			{"Informasi_Pengajuan_DIKDASMEN": ""}
		</form_data_view>
		<form_data_input>
			{"Laporan_Asesment_(include_berita_acara)_Assesor_1": "","Laporan_Keuangan_Assesor_1": ""}
		</form_data_input>
		<decision_key>
			{"true":"Selesai", "false": "Kembali", "save": "Simpan" }
		</decision_key>
		<statustiket>
			On Process
		</statustiket>
		<logtrue>
			Penilaian Visitasi,Dokumen kamu selesai proses penilaian visitasi oleh Assesor 1
		</logtrue>
		<steptrue>
			28
		</steptrue>
		<stepfalse>
			23
		</stepfalse>
	</step>
	<step>
		<number>
			24
		</number>
		<type>
			form
		</type>
		<role>
			DS
		</role>
		<title>
			Penilaian Visitasi Standar Kompetensi Lulusan Asesor 2
		</title>
		<viewer>
			SK,AD
		</viewer>
		<form_data_view>
			{"Informasi_Pengajuan_DIKDASMEN": "","Hasil_Pravisitasi":"" }
		</form_data_view>
		<form_data_input>
			{"Pencapaian_Tujuan_Pendidikan_asesor2": ""}
		</form_data_input>
		<decision_key>
			{"true":"Lanjutkan", "save": "Simpan"}
		</decision_key>
		<statustiket>
			On Process
		</statustiket>
		<logstart>
			Penilaian Visitasi,Dokumen kamu dalam proses penilaian visitasi oleh Assesor 2
		</logstart>
		<steptrue>
			25
		</steptrue>
		<stepfalse>
			15
		</stepfalse>
	</step>
	<step>
		<number>
			25
		</number>
		<type>
			form
		</type>
		<role>
			DS
		</role>
		<title>
			Penilaian Visitasi Standar Kurikulum Asesor 2
		</title>
		<viewer>
			SK,AD
		</viewer>
		<form_data_view>
			{"Informasi_Pengajuan_DIKDASMEN": "","Hasil_Pravisitasi":"" }
		</form_data_view>
		<form_data_input>
			{"Kepemimpinan_dan_Tata_Kelola_asesor2": "" }
		</form_data_input>
		<decision_key>
			{"true":"Lanjutkan", "false": "Kembali", "save": "Simpan" }
		</decision_key>
		<statustiket>
			On Process
		</statustiket>
		<steptrue>
			26
		</steptrue>
		<stepfalse>
			24
		</stepfalse>
	</step>
	<step>
		<number>
			26
		</number>
		<type>
			form
		</type>
		<role>
			DS
		</role>
		<title>
			Penilaian Visitasi Standar Pendidik dan Tenaga Kependidikan Asesor 2
		</title>
		<viewer>
			SK,AD
		</viewer>
		<form_data_view>
			{"Informasi_Pengajuan_DIKDASMEN": "" ,"Hasil_Pravisitasi":""}
		</form_data_view>
		<form_data_input>
			{"Kinerja_Pendidik_dalam_Pembelajaran_asesor2": ""}
		</form_data_input>
		<decision_key>
			{"true":"Lanjutkan", "false": "Kembali", "save": "Simpan" }
		</decision_key>
		<statustiket>
			On Process
		</statustiket>
		<steptrue>
			27
		</steptrue>
		<stepfalse>
			25
		</stepfalse>
	</step>
	<step>
		<number>
			27
		</number>
		<type>
			form
		</type>
		<role>
			DS
		</role>
		<title>
			Penilaian Visitasi Standar Kelembagaan Asesor 2
		</title>
		<viewer>
			SK,AD
		</viewer>
		<form_data_view>
			{"Informasi_Pengajuan_DIKDASMEN": "","Hasil_Pravisitasi":"" }
		</form_data_view>
		<form_data_input>
			{"Kepengasuhan_Pesantren_asesor2": ""}
		</form_data_input>
		<decision_key>
			{"true":"Lanjutkan", "false": "Kembali", "save": "Simpan" }
		</decision_key>
		<logtrue>
			Penilaian Visitasi,Dokumen kamu selesai proses penilaian visitasi oleh Assesor 2
		</logtrue>
		<statustiket>
			On Process
		</statustiket>
		<steptrue>
			51
		</steptrue>
		<stepfalse>
			26
		</stepfalse>
	</step>
	<step>
		<number>
			51
		</number>
		<type>
			form
		</type>
		<role>
			DS
		</role>
		<title>
			Penilaian Visitasi Asesor 2
		</title>
		<viewer>
			SK,AD
		</viewer>
		<form_data_view>
			{"Informasi_Pengajuan_DIKDASMEN": "" }
		</form_data_view>
		<form_data_input>
			{"Laporan_Asesment_(include_berita_acara)_Assesor_2": "","Laporan_Keuangan_Assesor_2": ""}
		</form_data_input>
		<decision_key>
			{"true":"Selesai", "false": "Kembali", "save": "Simpan" }
		</decision_key>
		<logtrue>
			Penilaian Visitasi,Dokumen kamu selesai proses penilaian visitasi oleh Assesor 2
		</logtrue>
		<statustiket>
			On Process
		</statustiket>
		<steptrue>
			28
		</steptrue>
		<stepfalse>
			27
		</stepfalse>
	</step>
	<step>
		<number>
			28
		</number>
		<type>
			system_decision
		</type>
		<variabela>
			Apakah_Visitasi_Asesor_1_Selesai
		</variabela>
		<operator>
			=
		</operator>
		<variabelb>
			Visitasi_selesai_yes
		</variabelb>
		<steptrue>
			30
		</steptrue>
		<stepfalse>
			20
		</stepfalse>
	</step>
	<step>
		<number>
			29
		</number>
		<type>
			system_decision
		</type>
		<variabela>
			Apakah_Visitasi_Asesor_2_Selesai
		</variabela>
		<operator>
			=
		</operator>
		<variabelb>
			Visitasi_selesai_yes
		</variabelb>
		<steptrue>
			30
		</steptrue>
		<stepfalse>
			24
		</stepfalse>
	</step>
	<step>
		<number>
			30
		</number>
		<type>
			system_decision
		</type>
		<variabela>
			Apakah_Visitasi_Asesor_1_Selesai
		</variabela>
		<operator>
			=
		</operator>
		<variabelb>
			Apakah_Visitasi_Asesor_2_Selesai
		</variabelb>
		<steptrue>
			34
		</steptrue>
		<stepfalse>
			31
		</stepfalse>
	</step>
	<step>
		<number>
			31
		</number>
		<type>
			system_kosong
		</type>
		<steptrue>
			0
		</steptrue>
		<stepfalse>
			0
		</stepfalse>
	</step>
	<step>
		<number>
			34
		</number>
		<type>
			system_kalkulasi_nilai_form
		</type>
		<steptrue>
			35
		</steptrue>
		<stepfalse>
			0
		</stepfalse>
	</step>
	<step>
		<number>
			35
		</number>
		<role>
			SK
		</role>
		<type>
			form
		</type>
		<title>
			Validasi Data Complianc
		</title>
		<viewer>
			AD
		</viewer>
		<form_data_view>
			{"Informasi_Pengajuan_DIKDASMEN": "" }
		</form_data_view>
		<form_data_input>
			{"Informasi_Syarat_Utama_dan_Khusus_validasi": "","Kualifikasi_Kepala_Satuan_Pendidikan_validasi": "","Kualifikasi_Akademik_Pendidik_validasi": "","Kualifikasi_Tenaga_Kependidikan_validasi": "","Sarana_Dan_Prasrana_Penunjang_Kegiatan_Pembelajaran_validasi": "","Sarana_Dan_Prasarana_Penunjang_Pengasuhan_validasi": "","Informasi_Statistik_Rasio_Santri_Dan_Pendidik_validasi":"" }
		</form_data_input>
		<decision_key>
			{"true":"Lanjutkan", "save": "Simpan"}
		</decision_key>
		<status>
			Sedang Diproses
		</status>
		<grup>
			On Process
		</grup>
		<statustiket>
			On Process
		</statustiket>
		<logstart>
			Validasi,Pengajuan SPME dalam proses validasi visitasi oleh Sekretariat MM
		</logstart>
		<steptrue>
			36
		</steptrue>
		<stepfalse>
			0
		</stepfalse>
	</step>
	<step>
		<number>
			36
		</number>
		<type>
			form
		</type>
		<role>
			SK
		</role>
		<title>
			Validasi Standar Kompetensi Lulusan Dewan Asessment
		</title>
		<viewer>
			AD
		</viewer>
		<form_data_view>
			{"Informasi_Pengajuan_DIKDASMEN": "" }
		</form_data_view>
		<form_data_input>
			{"Pencapaian_Tujuan_Pendidikan_validasi": "" }
		</form_data_input>
		<decision_key>
			{"true":"Lanjutkan", "save": "Simpan", "false": "Kembali"}
		</decision_key>
		<status>
			Sedang Diproses
		</status>
		<grup>
			On Process
		</grup>
		<statustiket>
			On Process
		</statustiket>
		<steptrue>
			37
		</steptrue>
		<stepfalse>
			35
		</stepfalse>
	</step>
	<step>
		<number>
			37
		</number>
		<type>
			form
		</type>
		<role>
			SK
		</role>
		<title>
			Validasi Standar Kurikulum Dewan Asessment
		</title>
		<viewer>
			AD
		</viewer>
		<form_data_view>
			{"Informasi_Pengajuan_DIKDASMEN": "" }
		</form_data_view>
		<form_data_input>
			{"Kepemimpinan_dan_Tata_Kelola_validasi": ""}
		</form_data_input>
		<decision_key>
			{"true":"Lanjutkan", "save": "Simpan", "false": "Kembali"}
		</decision_key>
		<statustiket>
			On Process
		</statustiket>
		<steptrue>
			38
		</steptrue>
		<stepfalse>
			36
		</stepfalse>
	</step>
	<step>
		<number>
			38
		</number>
		<type>
			form
		</type>
		<role>
			SK
		</role>
		<title>
			Validasi Standar Pendidik dan Tenaga Kependidikan Dewan Asessment
		</title>
		<viewer>
			AD
		</viewer>
		<form_data_view>
			{"Informasi_Pengajuan_DIKDASMEN": "" }
		</form_data_view>
		<form_data_input>
			{"Kinerja_Pendidik_dalam_Pembelajaran_validasi": ""}
		</form_data_input>
		<decision_key>
			{"true":"Lanjutkan", "save": "Simpan", "false": "Kembali"}
		</decision_key>
		<statustiket>
			On Process
		</statustiket>
		<steptrue>
			39
		</steptrue>
		<stepfalse>
			37
		</stepfalse>
	</step>
	<step>
		<number>
			39
		</number>
		<type>
			form
		</type>
		<role>
			SK
		</role>
		<title>
			Validasi Standar Kelembagaan Dewan Asessment
		</title>
		<viewer>
			AD
		</viewer>
		<form_data_view>
			{"Informasi_Pengajuan_DIKDASMEN": "" }
		</form_data_view>
		<form_data_input>
			{"Kepengasuhan_Pesantren_validasi": ""}
		</form_data_input>
		<decision_key>
			{"true":"Lanjutkan", "save": "Simpan", "false": "Kembali"}
		</decision_key>
		<statustiket>
			On Process
		</statustiket>
		<logtrue>
			Proses validasi Selesai, Dokumen SPME sudah selesai divalidasi oleh Sekretariat MM
		</logtrue>
		<steptrue>
			40
		</steptrue>
		<stepfalse>
			38
		</stepfalse>
	</step>
	<step>
		<number>
			40
		</number>
		<role>
			SK
		</role>
		<type>
			form
		</type>
		<title>
			Penetapan Hasil Visitasi (Pleno)
		</title>
		<viewer>
			AD
		</viewer>
		<form_data_view>
			{"Informasi_Pengajuan_DIKDASMEN": ""}
		</form_data_view>
		<form_data_input>
			{"Pencapaian_Tujuan_Pendidikan_pleno": "","Kepemimpinan_dan_Tata_Kelola_pleno": "","Kinerja_Pendidik_dalam_Pembelajaran_pleno": "","Kepengasuhan_Pesantren_pleno": ""}
		</form_data_input>
		<decision_key>
			{"true":"Lanjutkan", "save": "Simpan", "false": "Kembali"}
		</decision_key>
		<status>
			Sedang Diproses
		</status>
		<grup>
			On Process
		</grup>
		<statustiket>
			On Process
		</statustiket>
		<logstart>
			Penetapan Hasil Visitasi,Dokumen kamu dalam proses penetapan hasil visitasi oleh Sekretariat MM
		</logstart>
		<steptrue>
			41
		</steptrue>
		<stepfalse>
			40
		</stepfalse>
	</step>
	<step>
		<number>
			41
		</number>
		<type>
			system_kalkulasi_nilai_form_dikdasment
		</type>
		<title>
			totalnilai
		</title>
		<form_data_input>
			Keputusan_Akhir_Peringkat_Asessment
		</form_data_input>
		<form_data_view>
			status
		</form_data_view>
		<steptrue>
			42
		</steptrue>
		<stepfalse>
			0
		</stepfalse>
	</step>
	<step>
		<number>
			42
		</number>
		<role>
			SK
		</role>
		<type>
			form
		</type>
		<role>
			SK
		</role>
		<title>
			Penetapan Hasil Visitasi (Pleno)
		</title>
		<viewer>
			AD
		</viewer>
		<form_data_view>
			{"Informasi_Pengajuan_DIKDASMEN": "","Sumary_data_visitasi_dikdasmen": "","totalnilai":"" ,"Laporan_Asesment_(include_berita_acara)_Assesor_1": "","Laporan_Keuangan_Assesor_1": "","Laporan_Asesment_(include_berita_acara)_Assesor_2": "","Laporan_Keuangan_Assesor_2": ""}
		</form_data_view>
		<form_data_input>
			{"status": "","Keputusan_Akhir_Peringkat_Asessment": "" }
		</form_data_input>
		<decision_key>
			{"true":"Lanjutkan", "save": "Simpan", "false": "Kembali"}
		</decision_key>
		<status>
			Sedang Diproses
		</status>
		<grup>
			On Process
		</grup>
		<statustiket>
			On Process
		</statustiket>
		<logtrue>
			Penetapan Hasil Visitasi,Dokumen kamu selesai proses penetapan hasil visitasi oleh Sekretariat MM
		</logtrue>
		<steptrue>
			43
		</steptrue>
		<stepfalse>
			41
		</stepfalse>
	</step>
	<step>
		<number>
			43
		</number>
		<role>
			SK
		</role>
		<type>
			form
		</type>
		<role>
			SK
		</role>
		<title>
			Upload Sertifikat SPME
		</title>
		<viewer>
			AD
		</viewer>
		<form_data_view>
			{"Informasi_Pengajuan_DIKDASMEN": "","Sumary_data_visitasi": "","status": "","peringkat": ""}
		</form_data_view>
		<form_data_input>
			{"Sertifikat_SPME": "" }
		</form_data_input>
		<decision_key>
			{"true":"Lanjutkan" }
		</decision_key>
		<status>
			Sedang Diproses
		</status>
		<grup>
			On Process
		</grup>
		<statustiket>
			On Process
		</statustiket>
		<logstart>
			Penetapan Hasil Visitasi,Dokumen kamu dalam proses penetapan hasil visitasi oleh Sekretariat MM
		</logstart>
		<logtrue>
			Penetapan Hasil Visitasi,Dokumen kamu lulus visitasi oleh Sekretariat MM
		</logtrue>
		<logfalse>
			Penetapan Hasil Visitasi,Dokumen kamu tidak lulus visitasi oleh Sekretariat MM
		</logfalse>
		<steptrue>
			44
		</steptrue>
		<stepfalse>
			0
		</stepfalse>
	</step>
	<step>
		<number>
			44
		</number>
		<title>
			SeLesai SPME DIKDASMEN
		</title>
		<type>
			system_end
		</type>
		<steptrue>
			47
		</steptrue>
		<stepfalse>
			0
		</stepfalse>
	</step>
	<step>
		<number>
			46
		</number>
		<type>
			system_end
		</type>
		<steptrue>
			49
		</steptrue>
		<stepfalse>
			0
		</stepfalse>
	</step>
	<step>
		<number>
			47
		</number>
		<role>
			DD
		</role>
		<type>
			form
		</type>
		<title>
			Hasil SPME
		</title>
		<form_data_view>
			{"Informasi_Pengajuan_DIKDASMEN": "","Sumary_data_visitasi": "","status": "","peringkat": "","Sertifikat_SPME": ""}
		</form_data_view>
		<status>
			Selesai
		</status>
		<grup>
			Keputusan SPME
		</grup>
		<statustiket>
			On Process
		</statustiket>
		<logstart>
			Asement DIKDASMEN Selesai,Proses asesment DIKDASMEN Selesai
		</logstart>
		<steptrue>
			0
		</steptrue>
		<stepfalse>
			0
		</stepfalse>
	</step>
	<step>
		<number>
			49
		</number>
		<role>
			DD
		</role>
		<type>
			form
		</type>
		<title>
			SPME
		</title>
		<form_data_view>
			{"Informasi_Pengajuan_DIKDASMEN": "","Nama_Pesantren": "","Tahun_Berdiri": "" ,"Nomor_Statistik_Pesantren": "","Nama_Satuan_Pendidikan": "","NPSN": "","Jenjang": "","Alamat": "","Email": "","Contact_Person": "","Pimpinan_Pesantren": "","Pendiri_Pesantren": "","Ketua_Dewan_Masyayikh": "","Kepala_Satuan_Pendidikan": "","Tahun_Periode_Asesmen": ""}
		</form_data_view>
		<status>
			Dibatalkan
		</status>
		<grup>
			Dibatalkan
		</grup>
		<statustiket>
			Dibatalkan
		</statustiket>
		<logstart>
			SPME,pengajuan dibatalkan
		</logstart>
		<steptrue>
			0
		</steptrue>
		<stepfalse>
			0
		</stepfalse>
	</step>
	<step>
		<number>
			1000
		</number>
		<role>
			DS
		</role>
		<type>
			form
		</type>
		<title>
			SPME
		</title>
		<form_data_view>
			{"Informasi_Pengajuan_DIKDASMEN": "","Informasi_Syarat_Utama_dan_Khusus_validasi": "","Kualifikasi_Kepala_Satuan_Pendidikan_validasi": "","Kualifikasi_Akademik_Pendidik_validasi": "","Kualifikasi_Tenaga_Kependidikan_validasi": "","Sarana_Dan_Prasrana_Penunjang_Kegiatan_Pembelajaran_validasi": "","Sarana_Dan_Prasarana_Penunjang_Pengasuhan_validasi": "","Informasi_Statistik_Rasio_Santri_Dan_Pendidik_validasi":"" }
		</form_data_view>
	</step>
	<step>
		<number>
			101
		</number>
		<role>
			DD,TA,MM,MA,AT,AS,SK
		</role>
		<type>
			form
		</type>
		<title>
			Data pengajuan
		</title>
		<form_data_view>
			{"Informasi_Pengajuan_DIKDASMEN": "","Nama_Pesantren": "","Tahun_Berdiri": "" ,"Nomor_Statistik_Pesantren": "","Nama_Satuan_Pendidikan": "","NPSN": "","Jenjang": "","Alamat": "","Email": "","Contact_Person": "","Pimpinan_Pesantren": "","Pendiri_Pesantren": "","Ketua_Dewan_Masyayikh": "","Kepala_Satuan_Pendidikan": "","Tahun_Periode_Asesmen": ""}
		</form_data_view>
	</step>
	<step>
		<number>
			102
		</number>
		<role>
			SK,AD,TA,MM,AS,AT
		</role>
		<type>
			form
		</type>
		<title>
			Data Pravisitasi
		</title>
		<form_data_view>
			{"Informasi_Pengajuan_DIKDASMEN": "","Informasi_Syarat_Utama_dan_Khusus_validasi": "","Kualifikasi_Kepala_Satuan_Pendidikan_validasi": "","Kualifikasi_Akademik_Pendidik_validasi": "","Kualifikasi_Tenaga_Kependidikan_validasi": "","Sarana_Dan_Prasrana_Penunjang_Kegiatan_Pembelajaran_validasi": "","Sarana_Dan_Prasarana_Penunjang_Pengasuhan_validasi": "","Informasi_Statistik_Rasio_Santri_Dan_Pendidik_validasi":"" }
		</form_data_view>
	</step>
	<step>
		<number>
			103
		</number>
		<role>
			SK,AD,TA,MM,AT
		</role>
		<type>
			form
		</type>
		<title>
			Data visitasi
		</title>
		<form_data_view>
			{"Informasi_Pengajuan_DIKDASMEN": "","Pencapaian_Tujuan_Pendidikan_validasi": "","Kepemimpinan_dan_Tata_Kelola_validasi": "","Kinerja_Pendidik_dalam_Pembelajaran_validasi": "","Kepengasuhan_Pesantren_validasi": ""}
		</form_data_view>
	</step>
</Process_Definition>
